{
  "lastId": 8,
  "items": [
    {
      "id": 1,
      "eventId": 1,
      "name": "Luigi Hidayat",
      "visitorType": "umum",
      "employeeId": "",
      "email": "w@gmail.c",
      "ratings": {
        "overall": 5,
        "content": 5,
        "logistics": 5
      },
      "saran": "",
      "kritik": "",
      "createdAt": "2025-11-30T15:13:46.547Z"
    },
    {
      "id": 2,
      "eventId": 1,
      "name": "w",
      "visitorType": "umum",
      "employeeId": "",
      "email": "w@gmail.c",
      "ratings": {
        "overall": 5,
        "content": 5,
        "logistics": 5
      },
      "saran": "",
      "kritik": "",
      "createdAt": "2025-11-30T15:18:30.854Z"
    },
    {
      "id": 3,
      "eventId": 2,
      "name": "w",
      "visitorType": "umum",
      "employeeId": "",
      "email": "w@gmail.c",
      "ratings": {
        "overall": 5,
        "content": 5,
        "logistics": 5
      },
      "saran": "",
      "kritik": "",
      "createdAt": "2025-11-30T15:18:52.954Z"
    },
    {
      "id": 4,
      "eventId": 2,
      "name": "ww",
      "visitorType": "umum",
      "employeeId": "",
      "email": "w@gmail.c",
      "ratings": {
        "overall": 5,
        "content": 5,
        "logistics": 5
      },
      "saran": "",
      "kritik": "",
      "createdAt": "2025-11-30T15:18:57.929Z"
    },
    {
      "id": 5,
      "eventId": 1,
      "name": "Sylvester Luigi Hidayat",
      "visitorType": "umum",
      "employeeId": "",
      "email": "baru@gmail.com",
      "ratings": {
        "overall": 5,
        "content": 5,
        "logistics": 5
      },
      "saran": "11",
      "kritik": "1",
      "createdAt": "2025-11-30T15:21:48.148Z"
    },
    {
      "id": 6,
      "eventId": 1,
      "name": "Sylvester Luigi Hidayat",
      "visitorType": "umum",
      "employeeId": "",
      "email": "sylvester.hidayat@binus.ac.id",
      "ratings": {
        "overall": 5,
        "content": 5,
        "logistics": 5
      },
      "saran": "",
      "kritik": "",
      "createdAt": "2025-11-30T15:23:18.386Z"
    },
    {
      "id": 7,
      "eventId": 1,
      "name": "Sylvester Luigi Hidayatqqqq",
      "visitorType": "umum",
      "employeeId": "",
      "email": "w@gmail.c",
      "ratings": {
        "overall": 5,
        "content": 5,
        "logistics": 5
      },
      "saran": "",
      "kritik": "",
      "createdAt": "2025-11-30T15:27:35.939Z"
    },
    {
      "id": 8,
      "eventId": 1,
      "name": "w",
      "visitorType": "umum",
      "employeeId": "",
      "email": "w@gmail.c",
      "ratings": {
        "overall": 5,
        "content": 5,
        "logistics": 5
      },
      "saran": "",
      "kritik": "",
      "createdAt": "2025-11-30T15:33:19.690Z"
    }
  ]
}